<?xml version="1.0"?>
<!DOCTYPE hibernate-mapping PUBLIC "-//Hibernate/Hibernate Mapping DTD 3.0//EN"
"http://www.hibernate.org/dtd/hibernate-mapping-3.0.dtd">
<hibernate-mapping package="com.framgia.model">
  <class name="OrderProduct" table="order_products">
    <id name="id" column="id">
      <generator class="increment" />
    </id>

    <property name="price" type="float">
      <column name="price" default="0" />
    </property>
    <property name="quantity" type="integer">
      <column name="quantity" default="1" />
    </property>
    <property name="status" type="integer">
      <column name="status" default="0" />
    </property>

    <many-to-one name="order" class="Order">
      <column name="order_id" not-null="true" />
    </many-to-one>

    <many-to-one name="product" class="Product">
      <column name="product_id" not-null="true" />
    </many-to-one>
  </class>
</hibernate-mapping>
